README.rst
metadata.py
setup.py
spotimote.py
spotimote_pb2.py
./metadata.py
./spotimote.py
./spotimote_pb2.py
spotimote.egg-info/PKG-INFO
spotimote.egg-info/SOURCES.txt
spotimote.egg-info/dependency_links.txt
spotimote.egg-info/entry_points.txt
spotimote.egg-info/pbr.json
spotimote.egg-info/requires.txt
spotimote.egg-info/top_level.txt