Metadata-Version: 1.1
Name: spotimote
Version: 1.0.1
Summary: 
